digital_footprint/__init__.py
digital_footprint/scanner.py
digital_footprint-1.6.9.dist-info/METADATA
digital_footprint-1.6.9.dist-info/WHEEL
digital_footprint-1.6.9.dist-info/entry_points.txt
digital_footprint-1.6.9.dist-info/top_level.txt
digital_footprint-1.6.9.dist-info/RECORD
