Metadata-Version: 2.1
Name: digital-footprint
Version: 1.6.9
Summary: Digital Footprint Scanner: Free tool to extract useful information from an email.
Author: IvanMartin
Author-email: imartin.desarrollo@gmail.com
Classifier: Programming Language :: Python :: 3
Classifier: License :: OSI Approved :: MIT License
Classifier: Operating System :: OS Independent
Requires-Dist: requests
Requires-Dist: python-whois
Requires-Dist: dnspython
Requires-Dist: waybackpy
Requires-Dist: colorama
Requires-Dist: googlesearch-python
